mpslib/__init__.py
mpslib/eas.py
mpslib/mpslib.py
mpslib/plot.py
mpslib/trainingimages.py
mpslib/bin/install_latest_mpslib.sh
mpslib/bin/mps_genesim
mpslib/bin/mps_genesim.exe
mpslib/bin/mps_snesim_list
mpslib/bin/mps_snesim_list.exe
mpslib/bin/mps_snesim_tree
mpslib/bin/mps_snesim_tree.exe
scikit_mps-0.6.0.dist-info/LICENSE
scikit_mps-0.6.0.dist-info/METADATA
scikit_mps-0.6.0.dist-info/WHEEL
scikit_mps-0.6.0.dist-info/top_level.txt
scikit_mps-0.6.0.dist-info/RECORD
