Metadata-Version: 2.1
Name: scikit-mps
Version: 0.6.0
Summary: Multiple point statistical (MPS) simulation
Home-page: https://github.com/ergosimulation/mpslib/tree/master/scikit-mps
Author: Thomas Mejer Hansen
Author-email: thomas.mejer.hansen@gmail.com
License: LGPL
Keywords: geostatistics,simulation,MPS
License-File: LICENSE
Requires-Dist: numpy (>=1.0.2)
Requires-Dist: matplotlib (>=1.0.0)
Requires-Dist: scipy
Requires-Dist: panel
Requires-Dist: pyvista
